lektor_netlify.py
lektor_netlify-0.3.dist-info/METADATA
lektor_netlify-0.3.dist-info/WHEEL
lektor_netlify-0.3.dist-info/entry_points.txt
lektor_netlify-0.3.dist-info/top_level.txt
lektor_netlify-0.3.dist-info/RECORD
