Metadata-Version: 2.1
Name: lektor-netlify
Version: 0.3
Summary: Lektor plugin to publish your site with Netlify.
Home-page: https://github.com/nixjdm/lektor-netlify
Author: A. Jesse Jiryu Davis
Author-email: jesse@emptysquare.net
License: MIT
Keywords: Lektor plugin static-site blog netlify
Platform: UNKNOWN
Classifier: Environment :: Plugins
Classifier: Environment :: Web Environment
Classifier: Framework :: Lektor
Classifier: Intended Audience :: Developers
Classifier: License :: OSI Approved :: MIT License
